[{
		"sender":	"server",
		"content":	"mamad joined the channel!!"
	}, {
		"sender":	"server",
		"content":	"kop joined the channel!!"
	}, {
		"sender":	"server",
		"content":	"ko joined the channel!!"
	}, {
		"sender":	"mamad",
		"content":	"heeeellllooooooooo"
	}, {
		"sender":	"server",
		"content":	"kop left the channel!!"
	}, {
		"sender":	"server",
		"content":	"ko left the channel!!"
	}, {
		"sender":	"server",
		"content":	"mamad left the channel!!"
	}, {
		"sender":	"server",
		"content":	"ko joined the channel!!"
	}, {
		"sender":	"server",
		"content":	"kop joined the channel!!"
	}, {
		"sender":	"server",
		"content":	"mamad joined the channel!!"
	}, {
		"sender":	"server",
		"content":	"kop left the channel!!"
	}, {
		"sender":	"server",
		"content":	"mamad left the channel!!"
	}, {
		"sender":	"server",
		"content":	"ko left the channel!!"
	}]